AsheeshJandaFirst/__init__.py
AsheeshJandaFirst/add.py
AsheeshJandaFirst/substract.py
AsheeshJandaFirst/extras/__init__.py
AsheeshJandaFirst/extras/divide.py
AsheeshJandaFirst/extras/multiply.py
verysimplemodule/__init__.py
verysimplemodule/add.py
verysimplemodule/substract.py
verysimplemodule/extras/__init__.py
verysimplemodule/extras/divide.py
verysimplemodule/extras/multiply.py
AsheeshJandaFirst-0.0.1.dist-info/METADATA
AsheeshJandaFirst-0.0.1.dist-info/WHEEL
AsheeshJandaFirst-0.0.1.dist-info/top_level.txt
AsheeshJandaFirst-0.0.1.dist-info/RECORD
